[
  {
    "line": 2,
    "elements": [
      {
        "line": 4,
        "name": "",
        "description": "",
        "type": "background",
        "keyword": "Contexto",
        "steps": [
          {
            "result": {
              "duration": 3807811800,
              "status": "passed"
            },
            "line": 5,
            "name": "que a modal esteja sendo exibida",
            "match": {
              "location": "br.com.chronosacademy.steps.LoginSteps.queAModalEstejaSendoExibida()"
            },
            "keyword": "Dado "
          }
        ]
      },
      {
        "start_timestamp": "2021-10-23T14:00:05.788Z",
        "before": [
          {
            "result": {
              "duration": 2115662700,
              "status": "passed"
            },
            "match": {
              "location": "br.com.chronosacademy.steps.LoginSteps.iniciaNavegador()"
            }
          }
        ],
        "line": 58,
        "name": "Realizar login com usuario em branco",
        "description": "",
        "id": "login;realizar-login-com-\u003cidentificacao\u003e;;2",
        "after": [
          {
            "result": {
              "duration": 648331400,
              "status": "passed"
            },
            "match": {
              "location": "br.com.chronosacademy.steps.LoginSteps.fechaNavegador()"
            }
          }
        ],
        "type": "scenario",
        "keyword": "Esquema do Cenario",
        "steps": [
          {
            "result": {
              "duration": 81766900,
              "status": "passed"
            },
            "line": 50,
            "name": "os campos de login sejam preenchidos da seguinte forma",
            "match": {
              "location": "br.com.chronosacademy.steps.LoginSteps.osCamposDeLoginSejamPreenchidosDaSeguinteForma(java.util.Map\u003cjava.lang.String, java.lang.String\u003e)"
            },
            "rows": [
              {
                "cells": [
                  "login",
                  ""
                ]
              },
              {
                "cells": [
                  "password",
                  "senha"
                ]
              },
              {
                "cells": [
                  "remember",
                  "false"
                ]
              }
            ],
            "keyword": "Quando "
          },
          {
            "result": {
              "duration": 57844900,
              "status": "passed"
            },
            "line": 54,
            "name": "for realizado o click no botao sign in",
            "match": {
              "location": "br.com.chronosacademy.steps.LoginSteps.forRealizadoOClickNoBotaoSignIn()"
            },
            "keyword": "Quando "
          },
          {
            "result": {
              "duration": 33183500,
              "status": "passed"
            },
            "line": 55,
            "name": "o botao sign in deve permanecer desabilitado",
            "match": {
              "location": "br.com.chronosacademy.steps.LoginSteps.oBotaoSignInDevePermanecerDesabilitado()"
            },
            "keyword": "Entao "
          }
        ],
        "tags": [
          {
            "name": "@dadosEmBranco"
          }
        ]
      },
      {
        "line": 4,
        "name": "",
        "description": "",
        "type": "background",
        "keyword": "Contexto",
        "steps": [
          {
            "result": {
              "duration": 3822137900,
              "status": "passed"
            },
            "line": 5,
            "name": "que a modal esteja sendo exibida",
            "match": {
              "location": "br.com.chronosacademy.steps.LoginSteps.queAModalEstejaSendoExibida()"
            },
            "keyword": "Dado "
          }
        ]
      },
      {
        "start_timestamp": "2021-10-23T14:00:12.599Z",
        "before": [
          {
            "result": {
              "duration": 1556165300,
              "status": "passed"
            },
            "match": {
              "location": "br.com.chronosacademy.steps.LoginSteps.iniciaNavegador()"
            }
          }
        ],
        "line": 59,
        "name": "Realizar login com senha em branco",
        "description": "",
        "id": "login;realizar-login-com-\u003cidentificacao\u003e;;3",
        "after": [
          {
            "result": {
              "duration": 636759900,
              "status": "passed"
            },
            "match": {
              "location": "br.com.chronosacademy.steps.LoginSteps.fechaNavegador()"
            }
          }
        ],
        "type": "scenario",
        "keyword": "Esquema do Cenario",
        "steps": [
          {
            "result": {
              "duration": 146520600,
              "status": "passed"
            },
            "line": 50,
            "name": "os campos de login sejam preenchidos da seguinte forma",
            "match": {
              "location": "br.com.chronosacademy.steps.LoginSteps.osCamposDeLoginSejamPreenchidosDaSeguinteForma(java.util.Map\u003cjava.lang.String, java.lang.String\u003e)"
            },
            "rows": [
              {
                "cells": [
                  "login",
                  "chronos"
                ]
              },
              {
                "cells": [
                  "password",
                  ""
                ]
              },
              {
                "cells": [
                  "remember",
                  "true"
                ]
              }
            ],
            "keyword": "Quando "
          },
          {
            "result": {
              "duration": 45109700,
              "status": "passed"
            },
            "line": 54,
            "name": "for realizado o click no botao sign in",
            "match": {
              "location": "br.com.chronosacademy.steps.LoginSteps.forRealizadoOClickNoBotaoSignIn()"
            },
            "keyword": "Quando "
          },
          {
            "result": {
              "duration": 22411900,
              "status": "passed"
            },
            "line": 55,
            "name": "o botao sign in deve permanecer desabilitado",
            "match": {
              "location": "br.com.chronosacademy.steps.LoginSteps.oBotaoSignInDevePermanecerDesabilitado()"
            },
            "keyword": "Entao "
          }
        ],
        "tags": [
          {
            "name": "@dadosEmBranco"
          }
        ]
      }
    ],
    "name": "Login",
    "description": "",
    "id": "login",
    "keyword": "Funcionalidade",
    "uri": "file:src/test/resources/features/login.feature",
    "tags": []
  }
]